pyvolume/__init__.py
pyvolume/mod.py
pyvolume/pyvolume.py
volume_control-0.7.dist-info/LICENSE
volume_control-0.7.dist-info/METADATA
volume_control-0.7.dist-info/WHEEL
volume_control-0.7.dist-info/top_level.txt
volume_control-0.7.dist-info/RECORD
