Metadata-Version: 2.1
Name: volume-control
Version: 0.7
Summary: Light weight OS-agnostic volume controller for python
Author-email: Vignesh Sivanandha Rao <svignesh1793@gmail.com>
License: MIT License
Project-URL: Homepage, https://github.com/thevickypedia/volume-control
Project-URL: Docs, https://thevickypedia.github.io/volume-control
Project-URL: Source, https://github.com/thevickypedia/volume-control
Project-URL: Bug Tracker, https://github.com/thevickypedia/volume-control/issues
Project-URL: Release Notes, https://github.com/thevickypedia/volume-control/blob/main/release_notes.rst
Keywords: pyvolume,volume-controller
Classifier: License :: OSI Approved :: MIT License
Classifier: Programming Language :: Python :: 3
Classifier: Development Status :: 5 - Production/Stable
Classifier: Operating System :: MacOS :: MacOS X
Classifier: Operating System :: Microsoft :: Windows
Classifier: Operating System :: POSIX :: Linux
Classifier: Topic :: Terminals :: Terminal Emulators/X Terminals
Requires-Python: >=3
License-File: LICENSE
